tarandm_analytics/__init__.py
tarandm_analytics/attribute_evaluator/__init__.py
tarandm_analytics/attribute_evaluator/evaluate_attributes.py
tarandm_analytics/base_class.py
tarandm_analytics/examples/tarandm_model_development.ipynb
tarandm_analytics/export_predictive_model/__init__.py
tarandm_analytics/export_predictive_model/create_predictive_model.py
tarandm_analytics/export_predictive_model/model_visualization.py
tarandm_analytics/export_predictive_model/upload_model_to_gitlab.py
tarandm_analytics/plots/__init__.py
tarandm_analytics/plots/plot_functions.py
tarandm_analytics/utils.py
tarandm_analytics-0.1.11.dist-info/METADATA
tarandm_analytics-0.1.11.dist-info/WHEEL
tarandm_analytics-0.1.11.dist-info/RECORD
