Metadata-Version: 2.3
Name: tarandm_analytics
Version: 0.1.11
Summary: Package links analytics in Python with TaranDM software.
Author: Marek Teller
Author-email: mteller@taran.ai
Requires-Python: >=3.12
Classifier: Programming Language :: Python :: 3
Classifier: Programming Language :: Python :: 3.12
Classifier: Programming Language :: Python :: 3.13
Requires-Dist: deepdiff
Requires-Dist: furl
Requires-Dist: gitpython
Requires-Dist: llvmlite
Requires-Dist: matplotlib
Requires-Dist: numba
Requires-Dist: pandas
Requires-Dist: path
Requires-Dist: pep8
Requires-Dist: polars
Requires-Dist: pydantic
Requires-Dist: python-gitlab
Requires-Dist: requests
Requires-Dist: scikit-learn
Requires-Dist: shap
Requires-Dist: sklearn_pmml_model
Requires-Dist: structlog
Requires-Dist: xgboost
